{
  "$schema": "http://json-schema.org/draft-07/schema#",
  "$id": "https://peiffer-innovations.github.io/flutter_json_schemas/schemas/json_dynamic_widget/icon.json",
  "title": "Icon",
  "type": "object",
  "additionalProperties": false,
  "properties": {
    "applyTextScaling": {
      "anyOf": [
        {
          "type": "string"
        },
        {
          "type": "number"
        },
        {
          "type": "boolean"
        }
      ]
    },
    "blendMode": {
      "$ref": "https://peiffer-innovations.github.io/flutter_json_schemas/schemas/json_theme/blend_mode.json"
    },
    "color": {
      "$ref": "https://peiffer-innovations.github.io/flutter_json_schemas/schemas/json_theme/color.json"
    },
    "fill": {
      "anyOf": [
        {
          "type": "string"
        },
        {
          "type": "number"
        }
      ]
    },
    "grade": {
      "anyOf": [
        {
          "type": "string"
        },
        {
          "type": "number"
        }
      ]
    },
    "icon": {
      "anyOf": [
        {
          "type": "string"
        },
        {
          "$ref": "https://peiffer-innovations.github.io/flutter_json_schemas/schemas/json_theme/icon_data.json"
        }
      ]
    },
    "opticalSize": {
      "anyOf": [
        {
          "type": "string"
        },
        {
          "type": "number"
        }
      ]
    },
    "semanticLabel": {
      "type": "string"
    },
    "shadows": {
      "anyOf": [
        {
          "type": "string"
        },
        {
          "type": "number"
        },
        {
          "type": "boolean"
        },
        {
          "type": "object",
          "additionalProperties": true
        },
        {
          "type": "array",
          "items": {
            "type": "string"
          }
        },
        {
          "type": "array",
          "items": {
            "type": "number"
          }
        },
        {
          "type": "array",
          "items": {
            "type": "boolean"
          }
        },
        {
          "type": "array",
          "items": {
            "type": "object",
            "additionalProperties": true
          }
        }
      ]
    },
    "size": {
      "anyOf": [
        {
          "type": "string"
        },
        {
          "type": "number"
        }
      ]
    },
    "textDirection": {
      "$ref": "https://peiffer-innovations.github.io/flutter_json_schemas/schemas/json_theme/text_direction.json"
    },
    "weight": {
      "anyOf": [
        {
          "type": "string"
        },
        {
          "type": "number"
        }
      ]
    }
  },
  "required": [
    "icon"
  ]
}