{
  "$schema": "http://json-schema.org/draft-06/schema#",
  "$id": "https://peiffer-innovations.github.io/flutter_json_schemas/schemas/json_theme/range_slider_track_shape.json",
  "$comment": "https://api.flutter.dev/flutter/material/RangeSliderTrackShape-class.html",
  "title": "RangeSliderTrackShape",
  "type": "string",
  "oneOf": [
    {
      "type": "string",
      "enum": [
        "rectangular",
        "rounded"
      ]
    },
    {
      "type": "string",
      "pattern": "^\\{\\{.*\\}\\}$"
    },
    {
      "type": "string",
      "pattern": "##.*##$"
    }
  ]
}