{
  "$schema": "http://json-schema.org/draft-06/schema#",
  "$id": "https://peiffer-innovations.github.io/flutter_json_schemas/schemas/json_theme/material_state_property_size.json",
  "$comment": "https://api.flutter.dev/flutter/material/MaterialStateProperty-class.html",
  "title": "MaterialStatePropertySize",
  "type": "object",
  "properties": {
    "disabled": {
      "anyOf": [
        {
          "type": "string"
        },
        {
          "$ref": "https://peiffer-innovations.github.io/flutter_json_schemas/schemas/json_theme/size.json"
        }
      ]
    },
    "dragged": {
      "anyOf": [
        {
          "type": "string"
        },
        {
          "$ref": "https://peiffer-innovations.github.io/flutter_json_schemas/schemas/json_theme/size.json"
        }
      ]
    },
    "empty": {
      "anyOf": [
        {
          "type": "string"
        },
        {
          "$ref": "https://peiffer-innovations.github.io/flutter_json_schemas/schemas/json_theme/size.json"
        }
      ]
    },
    "error": {
      "anyOf": [
        {
          "type": "string"
        },
        {
          "$ref": "https://peiffer-innovations.github.io/flutter_json_schemas/schemas/json_theme/size.json"
        }
      ]
    },
    "focused": {
      "anyOf": [
        {
          "type": "string"
        },
        {
          "$ref": "https://peiffer-innovations.github.io/flutter_json_schemas/schemas/json_theme/size.json"
        }
      ]
    },
    "hovered": {
      "anyOf": [
        {
          "type": "string"
        },
        {
          "$ref": "https://peiffer-innovations.github.io/flutter_json_schemas/schemas/json_theme/size.json"
        }
      ]
    },
    "pressed": {
      "anyOf": [
        {
          "type": "string"
        },
        {
          "$ref": "https://peiffer-innovations.github.io/flutter_json_schemas/schemas/json_theme/size.json"
        }
      ]
    },
    "selected": {
      "anyOf": [
        {
          "type": "string"
        },
        {
          "$ref": "https://peiffer-innovations.github.io/flutter_json_schemas/schemas/json_theme/size.json"
        }
      ]
    }
  }
}