{
  "$schema": "http://json-schema.org/draft-07/schema#",
  "$id": "https://peiffer-innovations.github.io/flutter_json_schemas/schemas/json_theme/segmented_button_theme_data.json",
  "$comment": "https://api.flutter.dev/flutter/material/SegmentedButtonThemeData-class.html",
  "title": "SearchViewThemeData",
  "additionalProperties": false,
  "properties": {
    "selectedIcon": {
      "anyOf": [
        {
          "type": "string"
        },
        {
          "$ref": "https://peiffer-innovations.github.io/flutter_json_schemas/schemas/json_theme/icon.json"
        }
      ]
    },
    "style": {
      "anyOf": [
        {
          "type": "string"
        },
        {
          "$ref": "https://peiffer-innovations.github.io/flutter_json_schemas/schemas/json_theme/button_style.json"
        }
      ]
    }
  }
}